[
    {
        "frame_index": 9,
        "image_id": "",
        "bbox": [
            778.5,
            316.0,
            268.0,
            629.5
        ],
        "score": 1.0,
        "output_keypoints_2d": [
            [
                903.5349731445312,
                339.3414611816406
            ],
            [
                888.9130859375,
                327.03961181640625
            ],
            [
                882.118896484375,
                324.921630859375
            ],
            [
                871.2562866210938,
                343.78753662109375
            ],
            [
                855.2723999023438,
                341.3638610839844
            ],
            [
                905.4450073242188,
                348.1969909667969
            ],
            [
                865.8739624023438,
                346.9373474121094
            ],
            [
                871.1038208007812,
                413.261962890625
            ],
            [
                908.2655029296875,
                434.67840576171875
            ],
            [
                944.1279296875,
                519.9343872070312
            ],
            [
                1015.3310546875,
                577.3927001953125
            ],
            [
                0.0,
                0.0
            ],
            [
                0.0,
                0.0
            ],
            [
                0.0,
                0.0
            ],
            [
                0.0,
                0.0
            ],
            [
                0.0,
                0.0
            ],
            [
                0.0,
                0.0
            ],
            [
                0.0,
                0.0
            ],
            [
                0.0,
                0.0
            ],
            [
                0.0,
                0.0
            ],
            [
                0.0,
                0.0
            ],
            [
                0.0,
                0.0
            ],
            [
                0.0,
                0.0
            ],
            [
                0.0,
                0.0
            ],
            [
                0.0,
                0.0
            ],
            [
                0.0,
                0.0
            ],
            [
                0.0,
                0.0
            ],
            [
                0.0,
                0.0
            ],
            [
                0.0,
                0.0
            ],
            [
                0.0,
                0.0
            ],
            [
                0.0,
                0.0
            ],
            [
                851.6765747070312,
                425.1822204589844
            ],
            [
                822.3613891601562,
                525.930908203125
            ],
            [
                808.582763671875,
                628.38720703125
            ],
            [
                0.0,
                0.0
            ],
            [
                0.0,
                0.0
            ],
            [
                0.0,
                0.0
            ],
            [
                0.0,
                0.0
            ],
            [
                0.0,
                0.0
            ],
            [
                0.0,
                0.0
            ],
            [
                0.0,
                0.0
            ],
            [
                0.0,
                0.0
            ],
            [
                0.0,
                0.0
            ],
            [
                0.0,
                0.0
            ],
            [
                0.0,
                0.0
            ],
            [
                0.0,
                0.0
            ],
            [
                0.0,
                0.0
            ],
            [
                0.0,
                0.0
            ],
            [
                0.0,
                0.0
            ],
            [
                0.0,
                0.0
            ],
            [
                0.0,
                0.0
            ],
            [
                0.0,
                0.0
            ],
            [
                0.0,
                0.0
            ],
            [
                0.0,
                0.0
            ],
            [
                883.7999877929688,
                477.0570983886719
            ],
            [
                888.7924194335938,
                592.0926513671875
            ],
            [
                888.2257690429688,
                626.7852783203125
            ],
            [
                873.2902221679688,
                771.662353515625
            ],
            [
                847.4925537109375,
                922.6863403320312
            ],
            [
                827.7499389648438,
                931.351806640625
            ],
            [
                926.6543579101562,
                930.5057983398438
            ],
            [
                875.3477172851562,
                633.7275390625
            ],
            [
                897.718505859375,
                783.9749755859375
            ],
            [
                893.5397338867188,
                941.1697387695312
            ],
            [
                864.6787109375,
                945.5
            ],
            [
                971.0162963867188,
                945.5
            ],
            [
                876.3145751953125,
                497.7970275878906
            ],
            [
                876.7693481445312,
                550.4580688476562
            ]
        ]
    }
]